balbuzard/__init__.py
balbuzard/balbuzard.py
balbuzard/bbcrack.py
balbuzard/bbharvest.py
balbuzard/bbpatterns.py
balbuzard/bbtrans.py
balbuzard/plugins/bbz_sample_plugin.py
balbuzard/plugins/trans_sample_plugin.py
balbuzard_3-1.0.0.dist-info/LICENSE
balbuzard_3-1.0.0.dist-info/METADATA
balbuzard_3-1.0.0.dist-info/WHEEL
balbuzard_3-1.0.0.dist-info/entry_points.txt
balbuzard_3-1.0.0.dist-info/top_level.txt
balbuzard_3-1.0.0.dist-info/RECORD
