Metadata-Version: 2.2
Name: balbuzard-3
Version: 1.0.0
Summary: Package of malware analysis tools to extract patterns of interest from suspicious files, crack malware obfuscation such as XOR, ROL, etc by bruteforcing, and checking for those patterns.
Author-email: "Philippe Lagadec / Corey Forman (digitalsleuth)" <github@digitalsleuth.ca>
Maintainer-email: "Corey Forman (digitalsleuth)" <github@digitalsleuth.ca>
License: This license applies to the whole Balbuzard package including balbuzard, bbcrack, bbharvest and bbtrans.
Project-URL: Homepage, https://github.com/digitalsleuth/balbuzard
Keywords: digital forensics,dfir,malware,reverse,balbuzard,bbcrack,bbharvest,bbtrans
Classifier: Development Status :: 5 - Production/Stable
Classifier: Programming Language :: Python :: 3
Classifier: License :: OSI Approved :: BSD License
Classifier: Operating System :: OS Independent
Requires-Python: >=3.6
License-File: LICENSE
Requires-Dist: python-magic
Requires-Dist: yara-python
Requires-Dist: python-magic-win64; platform_system == "Windows"
